.gitignore
.travis.yml
CHANGELOG.rst
LICENSE-MIT
MANIFEST.in
README.rst
requirements-dev.txt
requirements.txt
run.sh
setup.cfg
setup.py
test.sh
slack_to_trello/__init__.py
slack_to_trello/__init__.pyc
slack_to_trello/model.py
slack_to_trello/model.pyc
slack_to_trello.egg-info/PKG-INFO
slack_to_trello.egg-info/SOURCES.txt
slack_to_trello.egg-info/dependency_links.txt
slack_to_trello.egg-info/pbr.json
slack_to_trello.egg-info/requires.txt
slack_to_trello.egg-info/top_level.txt
slack_to_trello/config/env
slack_to_trello/config/env.test
slack_to_trello/test/__init__.py
slack_to_trello/test/__init__.pyc
slack_to_trello/test/test.pyc