Metadata-Version: 1.1
Name: slack-to-trello
Version: 1.0.0
Summary: Perform Trello actions via slash commands in Slack
Home-page: https://github.com/underdogio/slack-to-trello
Author: Todd Wolfson
Author-email: todd@twolfson.com
License: MIT
Download-URL: https://github.com/underdogio/slack-to-trello/archive/master.zip
Keywords: slack,trello
Platform: UNKNOWN
Classifier: Development Status :: 3 - Alpha
Classifier: Intended Audience :: Developers
Classifier: License :: OSI Approved :: MIT License
Classifier: Operating System :: OS Independent
Classifier: Programming Language :: Python
Classifier: Programming Language :: Python :: 2.7
Classifier: Programming Language :: Python :: 3.3
Classifier: Programming Language :: Python :: 3.4
